{"policies": [{"comment": "Default policy from Anchore CLI", "rules": [{"action": "STOP", "gate": "DOCKERFILECHECK", "trigger": "NOFROM", "params": [], "id": "9c6a1d1f-36da-446a-a828-116ed38069d3"}, {"action": "STOP", "gate": "DOCKERFILECHECK", "trigger": "NOTAG", "params": [], "id": "8d3442d0-402d-4665-98aa-2173a6d3545b"}, {"action": "GO", "gate": "DOCKERFILECHECK", "trigger": "FROMSCRATCH", "params": [], "id": "72da4cba-94ab-4de7-9443-69d645eabcc4"}, {"action": "GO", "gate": "DOCKERFILECHECK", "trigger": "SUDO", "params": [], "id": "38ad4a03-afd6-4add-a6ef-bf4ab2106c74"}, {"action": "STOP", "gate": "DOCKERFILECHECK", "trigger": "EXPOSE", "params": [{"name": "DENIEDPORTS", "value": "22"}], "id": "25379abd-65eb-4add-aac0-be60002519ab"}, {"action": "WARN", "gate": "PKGDIFF", "trigger": "PKGADD", "params": [], "id": "765ff3d3-77e1-4ff1-a52a-6e0bf8eab6d3"}, {"action": "WARN", "gate": "PKGDIFF", "trigger": "PKGDEL", "params": [], "id": "0f93f5b9-540a-4cab-954e-f1a0b473a741"}, {"action": "STOP", "gate": "PKGDIFF", "trigger": "PKGVERSIONDIFF", "params": [], "id": "31eb6634-a83e-4d3e-8039-2fadc4b4758d"}, {"action": "STOP", "gate": "SUIDDIFF", "trigger": "SUIDMODEDIFF", "params": [], "id": "b6e6da61-b21c-499a-a70d-a00a97e82b59"}, {"action": "STOP", "gate": "SUIDDIFF", "trigger": "SUIDFILEADD", "params": [], "id": "d4a7a51e-33c4-4a83-b758-c6301493a4ec"}, {"action": "GO", "gate": "SUIDDIFF", "trigger": "SUIDFILEDEL", "params": [], "id": "a6f9cb69-a181-4302-8ca2-2285331935af"}, {"action": "GO", "gate": "ANCHORESEC", "trigger": "VULNUNKNOWN", "params": [], "id": "e0867ca2-66d2-4999-aeba-31da64754a7c"}, {"action": "GO", "gate": "ANCHORESEC", "trigger": "VULNLOW", "params": [], "id": "dbdbb3e8-a45d-43f1-b558-ced31f9211c2"}, {"action": "WARN", "gate": "ANCHORESEC", "trigger": "VULNMEDIUM", "params": [], "id": "77422a88-2a84-4454-967c-59b8c8f36464"}, {"action": "STOP", "gate": "ANCHORESEC", "trigger": "VULNHIGH", "params": [], "id": "d0959409-15c6-42fd-90b2-05f49ca9cca5"}, {"action": "STOP", "gate": "ANCHORESEC", "trigger": "VULNCRITICAL", "params": [], "id": "6fe10b89-fdef-4310-b383-3c560c797204"}, {"action": "WARN", "gate": "ANCHORESEC", "trigger": "UNSUPPORTEDDISTRO", "params": [], "id": "38092e38-a474-486c-85d7-318958ed4e6b"}], "version": "1_0", "name": "default", "id": "7dcbe180-2914-4723-89d4-20b6657f66eb"}], "mappings": [{"name": "default", "repository": "*", "image": {"type": "tag", "value": "*"}, "whitelist_ids": ["912937b6-05fb-472f-bfbe-834c3562f32d"], "registry": "*", "id": "1c010abe-b086-451c-a25b-54ff02fe5e89", "policy_id": "7dcbe180-2914-4723-89d4-20b6657f66eb"}], "created_at": 1493583553, "whitelists": [{"comment": "Default Global Whitelist", "items": [], "version": "1_0", "name": "Global Whitelist", "id": "912937b6-05fb-472f-bfbe-834c3562f32d"}], "version": "1_0", "last_modified": 1493916280, "id": "2170857d-b660-4b56-a1a7-06550bf02eb2", "name": "AnchoreUserDefault"}